design.sv
// Code your design here
module fifo(
  input  logic clk,
  input  logic rst,
  input  logic w_en,
  input  logic r_en,
  input  logic [7:0] data_in,
  output logic [7:0] data_out,
  output logic full,           
  output logic empty
);

  
  logic [3:0] wptr;
  logic [3:0] rptr;
  logic [4:0] count;          
  logic [7:0] mem [15:0];     
  
  

  assign full  = (count == 16);
  assign empty = (count == 0);
  
 
  always @(posedge clk or negedge rst)
  begin
      if(!rst) begin
          wptr  <= 0;
          rptr  <= 0;
          count <= 0;
          data_out <= 0;
      end 
      else begin
         
          if (w_en == 1 && full == 0) begin 
              mem[wptr] <= data_in;
              wptr      <= wptr + 1;
          end 
          
        
          if (r_en == 1 && empty == 0) begin 
              data_out <= mem[rptr];
              rptr     <= rptr + 1;
          end
          
         
          if (w_en && !full && !(r_en && !empty))
              count <= count + 1;
          else if (r_en && !empty && !(w_en && !full))
              count <= count - 1;
      end 
  end

endmodule

testbench.sv
// Code your testbench here
// or browse Examples
`timescale 1ns/1ps

module fifo_tb();
  
    logic clk;
    logic rst;
    logic w_en;
   logic r_en;
    logic [7:0] data_in;
   logic [7:0] data_out;
  logic full;          
   logic empty;
  
  
  fifo uut(
    .clk(clk),
    .rst(rst),
    .w_en(w_en),
    .r_en(r_en),
    .data_in(data_in),
    .data_out(data_out),
    .full(full),
    .empty(empty)
  );
  
  initial 
    begin 
      
      $dumpfile("fifo_tb.vcd");
      $dumpvars(0,fifo_tb);
      
    end 
  
  always #10 clk = ~clk;
  
  initial 
    begin 
     clk = 0; 
    rst = 0;     
    w_en = 0; 
    r_en = 0; 
    data_in = 0;
      
       #15 rst = 1; 
      
       @(posedge clk);  
    data_in = 8'hAA;
    w_en = 1;       
    @(posedge clk);  
    w_en = 0;        
    
  
    @(posedge clk);
    data_in = 8'hBB;
    w_en = 1;
    @(posedge clk);
    w_en = 0;

    #20;            

    
    @(posedge clk);
    r_en = 1;        
    @(posedge clk);
    r_en = 0;       

  
    @(posedge clk);
    r_en = 1;
    @(posedge clk);
    r_en = 0;
  
      #100
      
      $finish;
    end 
endmodule

fifo_tb.vcd
$date
    Feb  7, 2026  05:33:13
$end
$version
    TOOL:	xmsim	25.03-s001
$end
$timescale
    1 ps
$end

$scope module fifo_tb $end
$var reg       1 !    clk $end
$var reg       1 "    rst $end
$var reg       1 #    w_en $end
$var reg       1 $    r_en $end
$var reg       8 %    data_in [7:0] $end
$var reg       8 &    data_out [7:0] $end
$var reg       1 '    full $end
$var reg       1 (    empty $end

$scope module uut $end
$var wire      1 )    clk  $end
$var wire      1 *    rst  $end
$var wire      1 +    w_en  $end
$var wire      1 ,    r_en  $end
$var wire      8 -    data_in [7:0] $end
$var reg       8 .    data_out [7:0] $end
$var reg       1 /    full $end
$var reg       1 0    empty $end
$var reg       4 1    wptr [3:0] $end
$var reg       4 2    rptr [3:0] $end
$var reg       5 3    count [4:0] $end
$var reg       8 4    mem[15] [7:0] $end
$var reg       8 5    mem[14] [7:0] $end
$var reg       8 6    mem[13] [7:0] $end
$var reg       8 7    mem[12] [7:0] $end
$var reg       8 8    mem[11] [7:0] $end
$var reg       8 9    mem[10] [7:0] $end
$var reg       8 :    mem[9] [7:0] $end
$var reg       8 ;    mem[8] [7:0] $end
$var reg       8 <    mem[7] [7:0] $end
$var reg       8 =    mem[6] [7:0] $end
$var reg       8 >    mem[5] [7:0] $end
$var reg       8 ?    mem[4] [7:0] $end
$var reg       8 @    mem[3] [7:0] $end
$var reg       8 A    mem[2] [7:0] $end
$var reg       8 B    mem[1] [7:0] $end
$var reg       8 C    mem[0] [7:0] $end
$upscope $end

$upscope $end

$enddefinitions $end
$dumpvars
0!
0"
0#
0$
b0 %
b0 &
0'
1(
0)
0*
0+
0,
b0 -
b0 .
0/
10
b0 1
b0 2
b0 3
bx 4
bx 5
bx 6
bx 7
bx 8
bx 9
bx :
bx ;
bx <
bx =
bx >
bx ?
bx @
bx A
bx B
bx C
$end
#10000
1!
1)
#15000
1"
1*
#20000
0!
0)
#30000
1!
b10101010 %
1#
1+
b10101010 -
1)
b10101010 C
b1 1
b1 3
00
0(
#40000
0!
0)
#50000
1!
0#
0+
1)
#60000
0!
0)
#70000
1!
b10111011 %
1#
1+
b10111011 -
1)
b10111011 B
b10 1
b10 3
#80000
0!
0)
#90000
1!
0#
0+
1)
#100000
0!
0)
#110000
1!
1$
1,
1)
b10101010 .
b1 2
b1 3
b10101010 &
#120000
0!
0)
#130000
1!
0$
0,
1)
#140000
0!
0)
#150000
1!
1$
1,
1)
b10111011 .
b10 2
b0 3
10
1(
b10111011 &
#160000
0!
0)
#170000
1!
0$
0,
1)
